crepes/__init__.py
crepes/base.py
crepes/extras.py
crepes/martingales.py
crepes-0.9.0.dist-info/licenses/LICENSE
crepes-0.9.0.dist-info/METADATA
crepes-0.9.0.dist-info/WHEEL
crepes-0.9.0.dist-info/top_level.txt
crepes-0.9.0.dist-info/RECORD
