Metadata-Version: 2.4
Name: crepes
Version: 0.9.0
Summary: Conformal classifiers, regressors, and predictive systems (crepes)
Home-page: https://github.com/henrikbostrom/crepes
Author: Henrik Boström
Author-email: bostromh@kth.se
Project-URL: Bug Tracker, https://github.com//henrikbostrom/crepes/issues
Classifier: Programming Language :: Python :: 3
Classifier: License :: OSI Approved :: BSD License
Classifier: Operating System :: OS Independent
Requires-Python: >=3.10
License-File: LICENSE
Requires-Dist: numpy
Requires-Dist: pandas
Requires-Dist: scipy
Dynamic: author
Dynamic: author-email
Dynamic: classifier
Dynamic: description
Dynamic: description-content-type
Dynamic: home-page
Dynamic: license-file
Dynamic: project-url
Dynamic: requires-dist
Dynamic: requires-python
Dynamic: summary
